{
  "schema": "projectx_formal_check_targets_v1",
  "purpose": "Formal/checker target registry. These are obligations for Python/Sage/Z3/Lean or related tools; they are not solved unless a result record is added.",
  "status_vocab": [
    "DEFINED",
    "SOURCE_COVERAGE_IMPLEMENTED",
    "NOT_IMPLEMENTED",
    "FINITE_CHECK_PLANNED",
    "SMT_CHECK_PLANNED",
    "LEAN_CHECK_PLANNED",
    "OPEN",
    "FINITE_CHECK_IMPLEMENTED"
  ],
  "targets": [
    {
      "id": "CHK-COSMO-NESTING-POSSET",
      "claim_ids": [
        "EXT-COSMO-001",
        "EXT-COSMO-COMB-001"
      ],
      "rows": [
        "R3",
        "R9"
      ],
      "families": [
        "C"
      ],
      "checker_layer": "Python/Sage finite combinatorics; later Lean",
      "predicate": "Generated Matryoshka containment poset agrees with expected face-lattice order for small n and with theorem statement as source authority.",
      "failure_condition": "A generated Matryoshka cover relation does not match the expected refinement/containment order, or a face-label mapping is not anti-isomorphic.",
      "status": [
        "DEFINED",
        "FINITE_CHECK_PLANNED"
      ]
    },
    {
      "id": "CHK-COSMO-MOVE-CLASSES",
      "claim_ids": [
        "EXT-COSMO-001",
        "EXT-COSMO-COMB-001"
      ],
      "rows": [
        "R2",
        "R3"
      ],
      "families": [
        "C",
        "A",
        "M1"
      ],
      "checker_layer": "Python/Sage finite posets",
      "predicate": "Primitive cover moves in cosmohedron finite baselines split into more than one move class, unlike current A/M1 baselines.",
      "failure_condition": "Cosmohedron primitive cover moves collapse to one class under the chosen equivalence, or A/M1 show matching multiplicity under the same equivalence.",
      "status": [
        "DEFINED",
        "FINITE_CHECK_PLANNED"
      ]
    },
    {
      "id": "CHK-R12-SUBMODULAR-LAW",
      "claim_ids": [
        "EXT-COSMO-002"
      ],
      "rows": [
        "R12"
      ],
      "families": [
        "C",
        "GAssoc"
      ],
      "checker_layer": "implemented ledger/source submodular-law interface validator; later SMT/Z3 delta-domain model",
      "predicate": "delta_P + delta_P' <= delta_union + delta_intersection is represented with the correct domain conventions, including delta_full = 0.",
      "failure_condition": "The encoded law permits a violating assignment under declared positivity/domain constraints, or union/intersection conventions are inconsistent.",
      "status": [
        "DEFINED",
        "SOURCE_COVERAGE_IMPLEMENTED"
      ]
    },
    {
      "id": "CHK-R13-EQUALITY-LAYER",
      "claim_ids": [
        "EXT-COSMO-002",
        "EXT-COSMO-COMB-001"
      ],
      "rows": [
        "R13"
      ],
      "families": [
        "C",
        "GAssoc"
      ],
      "checker_layer": "implemented ledger/source equality-layer interface validator; later typed predicate / Lean-Z3 model",
      "predicate": "Classify equality status as intrinsic/native vs degenerative/saturation based on whether equality is part of the family definition or arises only by imposing extra constraints on a generic inequality layer.",
      "failure_condition": "The source-bound definitions do not support the intrinsic/degenerative distinction, or the distinction is representation-dependent.",
      "status": [
        "DEFINED",
        "SOURCE_COVERAGE_IMPLEMENTED"
      ]
    },
    {
      "id": "CHK-ASSOCIAHEDRON-UNIT-DESCENT",
      "claim_ids": [
        "EXT-SCAT-FORMS-001"
      ],
      "rows": [
        "R1"
      ],
      "families": [
        "A"
      ],
      "checker_layer": "Python/Sage noncrossing diagonal poset",
      "predicate": "Facet/cover descent in the associahedron baseline proceeds by adding/removing one compatible chord, yielding unit codimension steps.",
      "failure_condition": "Generated noncrossing chord poset contains a cover changing more than one chord under the chosen grading.",
      "status": [
        "DEFINED",
        "FINITE_CHECK_PLANNED"
      ]
    },
    {
      "id": "CHK-M1-SIGN-DESCENT",
      "claim_ids": [
        "EXT-AMP-2013-001",
        "EXT-INTO-AMP-2013-001",
        "EXT-BINARY-AMP-001"
      ],
      "rows": [
        "R1"
      ],
      "families": [
        "M1"
      ],
      "checker_layer": "Python finite sign-vector enumeration; later Lean",
      "predicate": "Boundary/descent steps in the m=1 sign-flip family are represented by unit changes in sign/vector boundary data within declared scope.",
      "failure_condition": "A cover/descent relation changes non-unit rank or requires an extra hidden move class under the formal sign-family model.",
      "status": [
        "DEFINED",
        "FINITE_CHECK_PLANNED"
      ]
    },
    {
      "id": "CHK-SURF-U-EQUATION",
      "claim_ids": [
        "EXT-SURF-COUNT-2023-001",
        "EXT-SURF-ALLMULT-2023-001",
        "EXT-SURF-001",
        "EXT-YUKAWA-SURF-2024-001"
      ],
      "rows": [
        "R1",
        "R7",
        "R9",
        "R10"
      ],
      "families": [
        "S",
        "YUKAWA"
      ],
      "checker_layer": "implemented ledger/source u-equation interface validator; later finite curve-intersection model",
      "predicate": "For extracted curve sets, u_C + product_D u_D^{#int(C,D)} = 1 is encoded with the correct intersection exponents, and surfaceology extensions preserve the declared curve-integral interface where claimed.",
      "failure_condition": "A curve set has missing/interpreted intersection data, equation exponents do not match source-defined intersection numbers, or an extension claim lacks the needed curve-integral interface.",
      "status": [
        "DEFINED",
        "SOURCE_COVERAGE_IMPLEMENTED"
      ]
    },
    {
      "id": "CHK-SURF-BINARY-BOUNDARY",
      "claim_ids": [
        "EXT-SURF-COUNT-2023-001",
        "EXT-SURF-001"
      ],
      "rows": [
        "R1",
        "R9"
      ],
      "families": [
        "S"
      ],
      "checker_layer": "implemented ledger/source binary-boundary interface validator; later positive-region SMT/inequality model",
      "predicate": "In positive region, u_C >= 0 plus u-equations force 0 <= u_C <= 1 and incompatible crossing variables approach 1 when u_C -> 0.",
      "failure_condition": "The encoded positive-region equations admit u outside [0,1] or fail incompatible-boundary behavior under source assumptions.",
      "status": [
        "DEFINED",
        "SOURCE_COVERAGE_IMPLEMENTED"
      ]
    },
    {
      "id": "CHK-SURF-TINY-TWO-CURVE-FIXTURE",
      "claim_ids": [
        "EXT-SURF-COUNT-2023-001",
        "EXT-SURF-001"
      ],
      "rows": [
        "R1",
        "R9"
      ],
      "families": [
        "S"
      ],
      "checker_layer": "implemented finite two-curve fixture validator; later larger finite curve-intersection families",
      "predicate": "For the declared two-curve crossing fixture, the encoded intersection exponents derive u_a + u_b - 1 = 0 and u_b + u_a - 1 = 0, sample points satisfy the equations in the positive region, and boundary limits force the crossing variable to one.",
      "failure_condition": "The tiny fixture equations, sample solutions, or boundary-forcing behavior fail under exact rational evaluation, or the fixture is promoted beyond its two-curve finite scope.",
      "status": [
        "DEFINED",
        "FINITE_CHECK_IMPLEMENTED"
      ]
    },
    {
      "id": "CHK-SURF-FINITE-FIXTURE-FAMILY",
      "claim_ids": [
        "EXT-SURF-COUNT-2023-001",
        "EXT-SURF-001"
      ],
      "rows": [
        "R1",
        "R9"
      ],
      "families": [
        "S"
      ],
      "checker_layer": "implemented finite fixture-family validator; later generated finite curve-intersection families",
      "predicate": "For the declared finite family of crossing-graph fixtures, intersection exponents derive the listed u-equations; exact rational sample points satisfy those equations in the positive region; and boundary witnesses force crossing variables to one.",
      "failure_condition": "A declared fixture equation, crossing exponent, sample solution, or boundary-forcing witness fails under exact rational evaluation, or the family is promoted beyond finite fixture scope.",
      "status": [
        "DEFINED",
        "FINITE_CHECK_IMPLEMENTED"
      ]
    },
    {
      "id": "CHK-SURF-GENERATED-GRAPH-FIXTURES",
      "claim_ids": [
        "EXT-SURF-COUNT-2023-001",
        "EXT-SURF-001"
      ],
      "rows": [
        "R1",
        "R9"
      ],
      "families": [
        "S"
      ],
      "checker_layer": "implemented generated finite simple-graph fixture validator; later source-faithful curve-intersection generator",
      "predicate": "For all generated simple crossing-graph fixtures on 1..4 vertices, maximal-independent-set binary witnesses satisfy u_v + product_neighbors u_w = 1 exactly, with positive-region values in {0,1} and boundary-zero vertices forcing neighbor variables to one.",
      "failure_condition": "A generated graph, maximal independent set witness, u-equation, positive-region value, or boundary-forcing condition fails under exact evaluation, or the generated graph abstraction is promoted beyond finite fixture scope.",
      "status": [
        "DEFINED",
        "FINITE_CHECK_IMPLEMENTED"
      ]
    },
    {
      "id": "CHK-SURF-POLYGON-CHORD-FIXTURES",
      "claim_ids": [
        "EXT-SURF-COUNT-2023-001",
        "EXT-SURF-001"
      ],
      "rows": [
        "R1",
        "R9"
      ],
      "families": [
        "S"
      ],
      "checker_layer": "implemented finite convex-polygon chord-intersection validator; later source-faithful surface curve generator",
      "predicate": "For convex polygons with n=4..7, internal chord crossing graphs derived by endpoint interleaving have maximal-noncrossing binary witnesses that satisfy u_chord + product_crossing_chords u = 1 exactly, with boundary-zero chords forcing crossing variables to one.",
      "failure_condition": "A generated polygon chord, crossing relation, maximal noncrossing witness, u-equation, or boundary-forcing condition fails under exact evaluation, or the polygon chord abstraction is promoted beyond finite fixture scope.",
      "status": [
        "DEFINED",
        "FINITE_CHECK_IMPLEMENTED"
      ]
    },
    {
      "id": "CHK-SCAFFOLD-KINEMATIC-SHIFT",
      "claim_ids": [
        "EXT-HIDDEN-ZEROS-2023-001",
        "EXT-SCAFFOLD-001",
        "EXT-BACKUS-2025-001"
      ],
      "rows": [
        "R7",
        "R9"
      ],
      "families": [
        "S",
        "A"
      ],
      "checker_layer": "implemented ledger/source bridge validator; later symbolic substitution checks",
      "predicate": "The scaffolded-gluon kinematic shift, hidden-zero bridge, and W_e/transmutation claims are represented as source-bound bridge claims without promoting them to equivalence of realization classes.",
      "failure_condition": "The shift/transmutation bridge is incomplete, index partition is inconsistent, or a bridge is promoted to realization equivalence without a separate comparator proof.",
      "status": [
        "DEFINED",
        "SOURCE_COVERAGE_IMPLEMENTED"
      ]
    },
    {
      "id": "CHK-SAME-BOUNDARY-DIFFERENT-BULK-CAUTION",
      "claim_ids": [
        "EXT-AMP-PRIME-001",
        "EXT-WILSON-POS-2024-001"
      ],
      "rows": [],
      "families": [
        "M1",
        "WILSON"
      ],
      "checker_layer": "implemented ledger/source caution validator; later formal witness model",
      "predicate": "Any comparator relying on boundary structure, logarithmic form, positivity, or bootstrap success alone must mark same-boundary/different-bulk or post-integration-caution risk as unresolved unless bulk/equivalence evidence is separately checked.",
      "failure_condition": "A realization equivalence is inferred from same boundary/log-form/positivity/bootstrap data without explicit bulk or representation equivalence evidence.",
      "status": [
        "DEFINED",
        "SOURCE_COVERAGE_IMPLEMENTED"
      ]
    },
    {
      "id": "CHK-REPRESENTATION-COMPARATOR",
      "claim_ids": [
        "EXT-MOM-AMP-2019-001",
        "EXT-LOOP-MOM-AMP-2022-001"
      ],
      "rows": [
        "R1",
        "R7"
      ],
      "families": [
        "MOM",
        "LOOP_MOM",
        "M1"
      ],
      "checker_layer": "implemented ledger/source representation-comparator validator; later symbolic/spinor-helicity checks",
      "predicate": "Momentum and loop-momentum amplituhedron claims are carried as representation-comparator records, separating same-physics claims from equality of geometric realization class.",
      "failure_condition": "A spinor-helicity or loop-momentum presentation is treated as the same realization class as the momentum-twistor amplituhedron without an explicit representation map and boundary/bulk compatibility check.",
      "status": [
        "DEFINED",
        "SOURCE_COVERAGE_IMPLEMENTED"
      ]
    },
    {
      "id": "CHK-POS-GEOM-CANONICAL-BOUNDARY-RECURSION",
      "claim_ids": [
        "EXT-POS-GEOM-2017-001",
        "EXT-POS-GEOM-2017-002"
      ],
      "rows": [
        "R7"
      ],
      "families": [
        "PG"
      ],
      "checker_layer": "implemented source-coverage validator; later Lean/formal residue model",
      "predicate": "Canonical-form source claims include boundary-only logarithmic singularity and recursive residue-on-boundary-to-canonical-form-on-boundary conditions.",
      "failure_condition": "The extracted source support does not include both boundary singularity and recursive residue conditions, or the claim is generalized beyond the source scope.",
      "status": [
        "DEFINED",
        "SOURCE_COVERAGE_IMPLEMENTED"
      ]
    },
    {
      "id": "CHK-S2STAR-READOUT-SOURCE-COVERAGE",
      "claim_ids": [
        "EXT-POS-GEOM-2017-001",
        "EXT-POS-GEOM-2017-002",
        "EXT-SCAT-FORMS-001",
        "EXT-INTO-AMP-2013-001"
      ],
      "rows": [
        "R7"
      ],
      "families": [
        "PG",
        "A",
        "M1"
      ],
      "checker_layer": "implemented ledger/source coverage validator",
      "predicate": "S2* readout support may cite positive-geometry canonical-boundary recursion, scattering forms, and amplituhedron cuts/faces only as partial source coverage, not as checked substrate realization.",
      "failure_condition": "S2* is promoted to checked or physical substrate status without a separate validator/proof artifact.",
      "status": [
        "DEFINED",
        "SOURCE_COVERAGE_IMPLEMENTED"
      ]
    },
    {
      "id": "CHK-POS-GEOM-TRIANGULATION-PUSHFORWARD",
      "claim_ids": [
        "EXT-POS-GEOM-2017-003"
      ],
      "rows": [
        "R7"
      ],
      "families": [
        "PG"
      ],
      "checker_layer": "implemented source-coverage validator; later finite examples",
      "predicate": "Triangulation/push-forward methods are recorded as canonical-form construction methods, not as formation-medium dynamics or substrate settling laws.",
      "failure_condition": "Triangulation or push-forward source language is promoted into a physical formation or settling law without additional evidence.",
      "status": [
        "DEFINED",
        "SOURCE_COVERAGE_IMPLEMENTED"
      ]
    },
    {
      "id": "CHK-PRIME-LOCAL-CARRIER-SOURCE-COVERAGE",
      "claim_ids": [
        "EXT-AMP-PRIME-002",
        "EXT-AMP-PRIME-003",
        "EXT-AMP-PRIME-004",
        "EXT-AMP-PRIME-005"
      ],
      "rows": [
        "R1",
        "R7",
        "R13"
      ],
      "families": [
        "M1",
        "Prime"
      ],
      "checker_layer": "ledger/source coverage guard planned; later finite sign-flip/chiral-octagon model if scoped",
      "predicate": "Prime local-carrier source claims about sign-flip local positive spaces, sign-flip-four/chiral-octagon regions, degenerations, and pentagon gluing are recorded as source-extracted positive-geometry facts only, without promotion to Formation Medium substrate, engineering feasibility, or universal carrier theorem.",
      "failure_condition": "A Prime sign-flip/chiral-octagon/gluing claim is used as physical substrate evidence, generalized beyond one-loop MHV/Prime scope, or treated as a formal carrier theorem without a separate checker.",
      "status": [
        "DEFINED",
        "NOT_IMPLEMENTED"
      ]
    }
  ]
}
