{
  "capture_origin": "real_dataset",
  "claim": "The CEF runtime can generate held-out predictions from construction-only constraints and be evaluated by a separate oracle.",
  "construction_packet_hash": "c36a37e0b8bd95b3b8a1e4a18cfc2f6651be3b7e56c6038ed20039fedfdcbd14",
  "construction_verifier_independence": {
    "construction_hash_ok": true,
    "distinct_hashes": true,
    "oracle_hash_ok": true,
    "same_feature_set": true,
    "split_ok": true,
    "status": "PASS"
  },
  "controls": [
    {
      "control": "random-runtime",
      "failed_as_expected": true,
      "passed": false,
      "reason": "random observables should not satisfy held-out individual-worm oracle"
    },
    {
      "control": "over-stable-runtime",
      "failed_as_expected": true,
      "passed": false,
      "reason": "over-stable runtime should fail held-out perturbation response"
    },
    {
      "control": "behavior-only-output",
      "failed_as_expected": true,
      "passed": false,
      "reason": "behavior-only output must fail if internal individual constraints fail"
    },
    {
      "control": "missing-construction-verifier-split",
      "failed_as_expected": true,
      "passed": false,
      "reason": "construction and verifier packets must be independent splits"
    },
    {
      "control": "runtime-cannot-absorb-construction-only-constraints",
      "failed_as_expected": true,
      "passed": false,
      "reason": "blind runtime must carry construction-fit model and absorbed internal constraints"
    },
    {
      "control": "verifier-oracle-leakage",
      "failed_as_expected": true,
      "passed": false,
      "reason": "blind projection must not use verifier oracle for generation"
    }
  ],
  "controls_failed_as_expected": true,
  "dataset_source": "Dryad DOI 10.5061/dryad.w9ghx3g4v copper-boundary H5",
  "heldout_driver_hash": "0d3260138ae23cad29526c4f5003c34f66476f9e09c8e6f0afbba43ff2f01afc",
  "heldout_driver_loaded": true,
  "heldout_perturbation_verification": {
    "passed_count": 16,
    "rows": [
      {
        "feature": "neural_mean",
        "oracle_range": [
          0.2951390918289934,
          0.39513909182899337
        ],
        "passed": false,
        "value": 0.4685955250329675
      },
      {
        "feature": "posture_mean",
        "oracle_range": [
          0.16576878105447818,
          0.26576878105447815
        ],
        "passed": true,
        "value": 0.2219464143105321
      },
      {
        "feature": "stimulus_mean",
        "oracle_range": [
          0.6376172607879924,
          0.7376172607879925
        ],
        "passed": true,
        "value": 0.6876174179137562
      },
      {
        "feature": "motor_mean",
        "oracle_range": [
          0.3198392594597199,
          0.4198392594597199
        ],
        "passed": true,
        "value": 0.3341442387990509
      },
      {
        "feature": "perturbation_response",
        "oracle_range": [
          0.5562541672628203,
          0.6562541672628204
        ],
        "passed": false,
        "value": 0.658092432491922
      },
      {
        "feature": "body_loop_coupling",
        "oracle_range": [
          0.24280402025709907,
          0.34280402025709905
        ],
        "passed": true,
        "value": 0.27804532655479147
      },
      {
        "feature": "delta_neural",
        "oracle_range": [
          0.41122860934176403,
          0.5112286093417641
        ],
        "passed": false,
        "value": 0.5197092197862371
      },
      {
        "feature": "delta_perturbation_response",
        "oracle_range": [
          0.42946897110222454,
          0.5294689711022246
        ],
        "passed": true,
        "value": 0.5096202424030138
      },
      {
        "feature": "delta_stimulus",
        "oracle_range": [
          0.47751719824890554,
          0.5775171982489056
        ],
        "passed": true,
        "value": 0.52751740290087
      },
      {
        "feature": "motor_slope",
        "oracle_range": [
          0.45176274658723176,
          0.5517627465872318
        ],
        "passed": true,
        "value": 0.4972892700457401
      },
      {
        "feature": "neural_lagged_response",
        "oracle_range": [
          0.44622765844368234,
          0.5462276584436824
        ],
        "passed": false,
        "value": 0.5537237088878613
      },
      {
        "feature": "neural_peak",
        "oracle_range": [
          0.36502087294603075,
          0.46502087294603073
        ],
        "passed": false,
        "value": 0.2755560743360077
      },
      {
        "feature": "neural_slope",
        "oracle_range": [
          0.28778505109083313,
          0.3877850510908331
        ],
        "passed": false,
        "value": 0.5478406399102842
      },
      {
        "feature": "neural_variance",
        "oracle_range": [
          0.0,
          0.07602250741387769
        ],
        "passed": true,
        "value": 0.013115209715878928
      },
      {
        "feature": "perturbation_response_auc",
        "oracle_range": [
          0.7531270836314101,
          0.8531270836314102
        ],
        "passed": true,
        "value": 0.8290461887743942
      },
      {
        "feature": "perturbation_response_decay",
        "oracle_range": [
          0.42946897110222454,
          0.5294689711022246
        ],
        "passed": true,
        "value": 0.5096202424030138
      },
      {
        "feature": "perturbation_response_peak",
        "oracle_range": [
          0.95,
          1.0
        ],
        "passed": true,
        "value": 0.9999999450568673
      },
      {
        "feature": "population_activity_dispersion",
        "oracle_range": [
          0.0,
          0.07602250741387769
        ],
        "passed": true,
        "value": 0.013115209715878928
      },
      {
        "feature": "posture_slope",
        "oracle_range": [
          0.44928979860850815,
          0.5492897986085081
        ],
        "passed": true,
        "value": 0.5010947666805887
      },
      {
        "feature": "previous_neural_mean",
        "oracle_range": [
          0.3726818731454653,
          0.4726818731454653
        ],
        "passed": true,
        "value": 0.42917703051735934
      },
      {
        "feature": "previous_perturbation_response",
        "oracle_range": [
          0.5973162250583712,
          0.6973162250583713
        ],
        "passed": true,
        "value": 0.638851892742761
      },
      {
        "feature": "previous_stimulus_mean",
        "oracle_range": [
          0.5825828642901814,
          0.6825828642901814
        ],
        "passed": true,
        "value": 0.6325825571688951
      }
    ],
    "status": "FAIL",
    "total_count": 22
  },
  "individual_capture_packet_loaded": true,
  "individual_id": "dryad_real_copper_v0_3_18_v0_3_leave_one_window_out_12",
  "oracle_hash": "aceebb62376b90119eb61ffa67c140d2a8a448c3dd5087a68b1fbff52094add4",
  "projection_hash": "e76438f6136170bf6feeb7ed3a2e3d88953c4af559629bc746af364f44402c41",
  "protocol": "CEF-v0.3",
  "real_organism_constraints_loaded": true,
  "report_hash": "0269ea88d2942748bb46aa3f35ad4a5808735c086267dfbf9a57ffa776b13ce1",
  "runtime_hash": "75a832646dc5b4113ca7e097bbc889e7b34aaf9a790cb75faeefdba4fef0e1ed",
  "runtime_used_oracle_for_generation": false,
  "schema": "cef-v0.1-blind-forcing-readiness-report",
  "status": "FAIL",
  "synthetic_worm_runtime_constrained": true,
  "verifier_blind_projection": true
}
